DWDocumentDB-1.0.0b2.dist-info/DESCRIPTION.rst
DWDocumentDB-1.0.0b2.dist-info/METADATA
DWDocumentDB-1.0.0b2.dist-info/RECORD
DWDocumentDB-1.0.0b2.dist-info/WHEEL
DWDocumentDB-1.0.0b2.dist-info/metadata.json
DWDocumentDB-1.0.0b2.dist-info/top_level.txt
dwdocumentdb/__init__.py
